yamlet.py
yamlet-0.2.0.dist-info/licenses/LICENSE
yamlet-0.2.0.dist-info/METADATA
yamlet-0.2.0.dist-info/WHEEL
yamlet-0.2.0.dist-info/top_level.txt
yamlet-0.2.0.dist-info/RECORD
