Metadata-Version: 2.4
Name: yamlet
Version: 0.2.0
Summary: A GCL-like templating engine for YAML
Home-page: https://github.com/JoshDreamland/Yamlet
Author: Josh Ventura
Author-email: JoshV10@gmail.com
Classifier: Programming Language :: Python :: 3
Classifier: License :: OSI Approved :: MIT License
Classifier: Operating System :: OS Independent
Requires-Python: >=3.10
License-File: LICENSE
Requires-Dist: ruamel.yaml>=0.17.0
Dynamic: author
Dynamic: author-email
Dynamic: classifier
Dynamic: description
Dynamic: description-content-type
Dynamic: home-page
Dynamic: license-file
Dynamic: requires-dist
Dynamic: requires-python
Dynamic: summary
